MANIFEST.in
README.rst
setup.cfg
setup.py
notifyAll/__init__.py
notifyAll/settings.py
notifyAll/providers/__init__.py
notifyAll/providers/base.py
notifyAll/providers/gmail/__init__.py
notifyAll/providers/gmail/provider.py
notifyAll/providers/msg91/__init__.py
notifyAll/providers/msg91/provider.py
notifyAll/providers/plivo/__init__.py
notifyAll/providers/plivo/provider.py
notifyAll/providers/sendgrid/__init__.py
notifyAll/providers/sendgrid/provider.py
notifyAll/providers/twilio/__init__.py
notifyAll/providers/twilio/provider.py
notifyAll/services/__init__.py
notifyAll/services/notifier.py
notifyAll/test/__init__.py
notifyAll/test/test_providers.py
notifyAll/test/test_service.py
python_notifyAll.egg-info/PKG-INFO
python_notifyAll.egg-info/SOURCES.txt
python_notifyAll.egg-info/dependency_links.txt
python_notifyAll.egg-info/top_level.txt