Metadata-Version: 1.1
Name: python-notifyAll
Version: 0.5
Summary: A library which you can use for all types of notifications like SMS, Mail, Push.
Home-page: https://github.com/inforian/python-notifyAll
Author: Neeraj Dhiman
Author-email: ndhiman08@gmail.com
License: GPL
Download-URL: https://github.com/inforian/python-notifyAll/archive/v0.5.tar.gz
Keywords: notification,notify,sms,email,push
Platform: UNKNOWN
